AUTHORS.rst
LICENSE
MANIFEST.in
README.rst
setup.py
django_sr.egg-info/PKG-INFO
django_sr.egg-info/SOURCES.txt
django_sr.egg-info/dependency_links.txt
django_sr.egg-info/not-zip-safe
django_sr.egg-info/requires.txt
django_sr.egg-info/top_level.txt
sr/__init__.py
sr/models.py
sr/templatetags/__init__.py
sr/templatetags/sr.py